app-d.py
app_d.py
server.py
app_d-0.2.3.dist-info/DESCRIPTION.rst
app_d-0.2.3.dist-info/METADATA
app_d-0.2.3.dist-info/RECORD
app_d-0.2.3.dist-info/WHEEL
app_d-0.2.3.dist-info/entry_points.txt
app_d-0.2.3.dist-info/metadata.json
app_d-0.2.3.dist-info/top_level.txt
