Metadata-Version: 2.0
Name: app-d
Version: 0.2.3
Summary: Automated Python Push-Deploy
Home-page: https://github.com/foxxyz/app-d
Author: Ivo Janssen
Author-email: hello@ivo.la
License: MIT
Download-URL: https://github.com/foxxyz/app-d/tarball/0.2.3
Keywords: deployment,git,push-deploy
Platform: UNKNOWN
Classifier: Development Status :: 3 - Alpha
Classifier: Environment :: Console
Classifier: Intended Audience :: Developers
Classifier: Topic :: Utilities
Classifier: Topic :: Software Development :: Version Control
Classifier: Topic :: System :: Systems Administration
Classifier: License :: OSI Approved :: MIT License
Requires-Dist: paramiko
